{
  "listings": [
    {
      "id": "1",
      "title": "Bright Studio near HKUST",
      "address": "Pak Sha Wan, Sai Kung",
      "district": "Sai Kung",
      "price": 9800,
      "size_sqft": 280,
      "bedrooms": 1,
      "available_from": "2026-03-01",
      "features": ["Furnished", "WiFi included", "Near shuttle bus"],
      "landlord_rating": 4.2,
      "verified": true,
      "source_url": "https://squarefoot.com.hk/example1",
      "scraped_at": "2026-02-28T10:00:00Z"
    },
    {
      "id": "2",
      "title": "Spacious Flat, MTR 5 min",
      "address": "Sha Tin Town Centre",
      "district": "Sha Tin",
      "price": 11500,
      "size_sqft": 420,
      "bedrooms": 2,
      "available_from": "2026-03-15",
      "features": ["Balcony", "Pet friendly", "New renovation"],
      "landlord_rating": 3.8,
      "verified": true,
      "source_url": "https://squarefoot.com.hk/example2",
      "scraped_at": "2026-02-28T10:00:00Z"
    },
    {
      "id": "3",
      "title": "Cozy Room, Quiet Street",
      "address": "Tuen Mun Town Plaza area",
      "district": "Tuen Mun",
      "price": 6200,
      "size_sqft": 180,
      "bedrooms": 1,
      "available_from": "2026-03-01",
      "features": ["Bills included", "Near LRT"],
      "landlord_rating": 4.6,
      "verified": false,
      "source_url": "https://spacious.hk/example3",
      "scraped_at": "2026-02-28T10:00:00Z"
    },
    {
      "id": "4",
      "title": "Modern Studio, Sea View",
      "address": "Clear Water Bay Road",
      "district": "Clear Water Bay",
      "price": 13000,
      "size_sqft": 320,
      "bedrooms": 1,
      "available_from": "2026-04-01",
      "features": ["Sea view", "Gym", "Concierge"],
      "landlord_rating": 4.9,
      "verified": true,
      "source_url": "https://squarefoot.com.hk/example4",
      "scraped_at": "2026-02-28T10:00:00Z"
    },
    {
      "id": "5",
      "title": "Budget Room, Student Area",
      "address": "Tai Po Market, near university bus",
      "district": "Tai Po",
      "price": 5800,
      "size_sqft": 150,
      "bedrooms": 1,
      "available_from": "2026-03-01",
      "features": ["Students welcome", "Quiet", "Near MTR"],
      "landlord_rating": 3.5,
      "verified": false,
      "source_url": "https://spacious.hk/example5",
      "scraped_at": "2026-02-28T10:00:00Z"
    },
    {
      "id": "6",
      "title": "Large 2BR, Family Building",
      "address": "Sai Kung Town Centre",
      "district": "Sai Kung",
      "price": 15500,
      "size_sqft": 580,
      "bedrooms": 2,
      "available_from": "2026-03-20",
      "features": ["Furnished", "Parking", "Near market"],
      "landlord_rating": 4.1,
      "verified": true,
      "source_url": "https://squarefoot.com.hk/example6",
      "scraped_at": "2026-02-28T10:00:00Z"
    }
  ]
}
